rpkimancer_sig/__init__.py
rpkimancer_sig/conjure.py
rpkimancer_sig/eecert.py
rpkimancer_sig/py.typed
rpkimancer_sig/sigobj.py
rpkimancer_sig/asn1/RpkiSignedChecklist-2022.asn
rpkimancer_sig/asn1/__init__.py
rpkimancer_sig-0.11.0.dist-info/METADATA
rpkimancer_sig-0.11.0.dist-info/WHEEL
rpkimancer_sig-0.11.0.dist-info/entry_points.txt
rpkimancer_sig-0.11.0.dist-info/top_level.txt
rpkimancer_sig-0.11.0.dist-info/RECORD
