Metadata-Version: 2.1
Name: rpkimancer-sig
Version: 0.11.0
Summary: A rpkimancer plugin providing support for Signed Checklists
Author: Ben Maddison
Author-email: benm@workonline.africa
License: MIT
Keywords: rpki,draft-ietf-sidrops-rpki-rsc
Classifier: License :: OSI Approved :: MIT License
Classifier: Programming Language :: Python :: 3
Classifier: Programming Language :: Python :: 3.8
Classifier: Programming Language :: Python :: 3.9
Requires-Python: >=3.8
Requires-Dist: rpkimancer (<0.3.0,>=0.2.1)
